{
    "key": "group_link_icon",
    "title": "[STORE] - Lien + icône",
    "fields": [
        {
            "key": "field_5e393cd74b7ea",
            "label": "",
            "name": "links",
            "type": "repeater",
            "instructions": "",
            "required": 0,
            "conditional_logic": 0,
            "wrapper": {
                "width": "",
                "class": "",
                "id": ""
            },
            "collapsed": "",
            "min": 0,
            "max": 0,
            "layout": "block",
            "button_label": "Ajouter un lien",
            "sub_fields": [
                {
                    "key": "field_5e393cd74d23b",
                    "label": "Icône",
                    "name": "woody_icon",
                    "type": "select",
                    "instructions": "",
                    "required": 0,
                    "conditional_logic": 0,
                    "wrapper": {
                        "width": "20",
                        "class": "",
                        "id": ""
                    },
                    "choices": {
                        "wicon-023-ampoule": "<div class=\"wicon-select\"><span class=\"wicon-woody-icons wicon-023-ampoule\"><\/span><span>Ampoule<\/span><\/div>",
                        "wicon-005-pinterest": "<div class=\"wicon-select\"><span class=\"wicon-woody-icons wicon-005-pinterest\"><\/span><span>Pinterest<\/span><\/div>",
                        "wicon-046-bas": "<div class=\"wicon-select\"><span class=\"wicon-woody-icons wicon-046-bas\"><\/span><span>Bas<\/span><\/div>",
                        "wicon-059-favoris-moins": "<div class=\"wicon-select\"><span class=\"wicon-woody-icons wicon-059-favoris-moins\"><\/span><span>Favoris moins<\/span><\/div>",
                        "wicon-015-horloge": "<div class=\"wicon-select\"><span class=\"wicon-woody-icons wicon-015-horloge\"><\/span><span>Horloge<\/span><\/div>",
                        "wicon-011-instagram": "<div class=\"wicon-select\"><span class=\"wicon-woody-icons wicon-011-instagram\"><\/span><span>Instagram<\/span><\/div>",
                        "wicon-036-citation-01": "<div class=\"wicon-select\"><span class=\"wicon-woody-icons wicon-036-citation-01\"><\/span><span>Citation 01<\/span><\/div>",
                        "wicon-028-plus-02": "<div class=\"wicon-select\"><span class=\"wicon-woody-icons wicon-028-plus-02\"><\/span><span>Plus 02<\/span><\/div>",
                        "wicon-009-vimeo": "<div class=\"wicon-select\"><span class=\"wicon-woody-icons wicon-009-vimeo\"><\/span><span>Vimeo<\/span><\/div>",
                        "wicon-063-checked": "<div class=\"wicon-select\"><span class=\"wicon-woody-icons wicon-063-checked\"><\/span><span>Checked<\/span><\/div>",
                        "wicon-027-restaurant": "<div class=\"wicon-select\"><span class=\"wicon-woody-icons wicon-027-restaurant\"><\/span><span>Restaurant<\/span><\/div>",
                        "wicon-047-fleche-haut": "<div class=\"wicon-select\"><span class=\"wicon-woody-icons wicon-047-fleche-haut\"><\/span><span>Fleche haut<\/span><\/div>",
                        "wicon-048-fleche-bas": "<div class=\"wicon-select\"><span class=\"wicon-woody-icons wicon-048-fleche-bas\"><\/span><span>Fleche bas<\/span><\/div>",
                        "wicon-003-google": "<div class=\"wicon-select\"><span class=\"wicon-woody-icons wicon-003-google\"><\/span><span>Google<\/span><\/div>",
                        "wicon-018-agenda": "<div class=\"wicon-select\"><span class=\"wicon-woody-icons wicon-018-agenda\"><\/span><span>Agenda<\/span><\/div>",
                        "wicon-062-crayon": "<div class=\"wicon-select\"><span class=\"wicon-woody-icons wicon-062-crayon\"><\/span><span>Crayon<\/span><\/div>",
                        "wicon-002-twitter": "<div class=\"wicon-select\"><span class=\"wicon-woody-icons wicon-002-twitter\"><\/span><span>Twitter<\/span><\/div>",
                        "wicon-019-oeuil": "<div class=\"wicon-select\"><span class=\"wicon-woody-icons wicon-019-oeuil\"><\/span><span>Oeuil<\/span><\/div>",
                        "wicon-033-coeur": "<div class=\"wicon-select\"><span class=\"wicon-woody-icons wicon-033-coeur\"><\/span><span>Coeur<\/span><\/div>",
                        "wicon-016-bulle": "<div class=\"wicon-select\"><span class=\"wicon-woody-icons wicon-016-bulle\"><\/span><span>Bulle<\/span><\/div>",
                        "wicon-053-tripadvisor": "<div class=\"wicon-select\"><span class=\"wicon-woody-icons wicon-053-tripadvisor\"><\/span><span>Tripadvisor<\/span><\/div>",
                        "wicon-029-croix-fermer": "<div class=\"wicon-select\"><span class=\"wicon-woody-icons wicon-029-croix-fermer\"><\/span><span>Croix fermer<\/span><\/div>",
                        "wicon-000-facebook": "<div class=\"wicon-select\"><span class=\"wicon-woody-icons wicon-000-facebook\"><\/span><span>Facebook<\/span><\/div>",
                        "wicon-031-etoile-pleine": "<div class=\"wicon-select\"><span class=\"wicon-woody-icons wicon-031-etoile-pleine\"><\/span><span>Etoile pleine<\/span><\/div>",
                        "wicon-044-enveloppe": "<div class=\"wicon-select\"><span class=\"wicon-woody-icons wicon-044-enveloppe\"><\/span><span>Enveloppe<\/span><\/div>",
                        "wicon-043-phone": "<div class=\"wicon-select\"><span class=\"wicon-woody-icons wicon-043-phone\"><\/span><span>Phone<\/span><\/div>",
                        "wicon-021-info": "<div class=\"wicon-select\"><span class=\"wicon-woody-icons wicon-021-info\"><\/span><span>Info<\/span><\/div>",
                        "wicon-022-itineraire": "<div class=\"wicon-select\"><span class=\"wicon-woody-icons wicon-022-itineraire\"><\/span><span>Itineraire<\/span><\/div>",
                        "wicon-014-livre": "<div class=\"wicon-select\"><span class=\"wicon-woody-icons wicon-014-livre\"><\/span><span>Livre<\/span><\/div>",
                        "wicon-055-vtt": "<div class=\"wicon-select\"><span class=\"wicon-woody-icons wicon-055-vtt\"><\/span><span>Vtt<\/span><\/div>",
                        "wicon-051-mal-voyant": "<div class=\"wicon-select\"><span class=\"wicon-woody-icons wicon-051-mal-voyant\"><\/span><span>Mal voyant<\/span><\/div>",
                        "wicon-058-favoris-plus": "<div class=\"wicon-select\"><span class=\"wicon-woody-icons wicon-058-favoris-plus\"><\/span><span>Favoris plus<\/span><\/div>",
                        "wicon-037-citation-02": "<div class=\"wicon-select\"><span class=\"wicon-woody-icons wicon-037-citation-02\"><\/span><span>Citation 02<\/span><\/div>",
                        "wicon-010-flickr": "<div class=\"wicon-select\"><span class=\"wicon-woody-icons wicon-010-flickr\"><\/span><span>Flickr<\/span><\/div>",
                        "wicon-061-corbeille": "<div class=\"wicon-select\"><span class=\"wicon-woody-icons wicon-061-corbeille\"><\/span><span>Corbeille<\/span><\/div>",
                        "wicon-007-viadeo": "<div class=\"wicon-select\"><span class=\"wicon-woody-icons wicon-007-viadeo\"><\/span><span>Viadeo<\/span><\/div>",
                        "wicon-045-haut": "<div class=\"wicon-select\"><span class=\"wicon-woody-icons wicon-045-haut\"><\/span><span>Haut<\/span><\/div>",
                        "wicon-053-loupe-par-defaut": "<div class=\"wicon-select\"><span class=\"wicon-woody-icons wicon-053-loupe-par-defaut\"><\/span><span>Loupe par defaut<\/span><\/div>",
                        "wicon-049-mobilité-réduite": "<div class=\"wicon-select\"><span class=\"wicon-woody-icons wicon-049-mobilité-réduite\"><\/span><span>Mobilité réduite<\/span><\/div>",
                        "wicon-008-snapchat": "<div class=\"wicon-select\"><span class=\"wicon-woody-icons wicon-008-snapchat\"><\/span><span>Snapchat<\/span><\/div>",
                        "wicon-026-precedent": "<div class=\"wicon-select\"><span class=\"wicon-woody-icons wicon-026-precedent\"><\/span><span>Precedent<\/span><\/div>",
                        "wicon-025-suivant": "<div class=\"wicon-select\"><span class=\"wicon-woody-icons wicon-025-suivant\"><\/span><span>Suivant<\/span><\/div>",
                        "wicon-012-smiley-bien": "<div class=\"wicon-select\"><span class=\"wicon-woody-icons wicon-012-smiley-bien\"><\/span><span>Smiley bien<\/span><\/div>",
                        "wicon-001-facebook-messenger": "<div class=\"wicon-select\"><span class=\"wicon-woody-icons wicon-001-facebook-messenger\"><\/span><span>Facebook messenger<\/span><\/div>",
                        "wicon-054-bike": "<div class=\"wicon-select\"><span class=\"wicon-woody-icons wicon-054-bike\"><\/span><span>Bike<\/span><\/div>",
                        "wicon-034-fleche-suivant": "<div class=\"wicon-select\"><span class=\"wicon-woody-icons wicon-034-fleche-suivant\"><\/span><span>Fleche suivant<\/span><\/div>",
                        "wicon-020-photos": "<div class=\"wicon-select\"><span class=\"wicon-woody-icons wicon-020-photos\"><\/span><span>Photos<\/span><\/div>",
                        "wicon-039-pin": "<div class=\"wicon-select\"><span class=\"wicon-woody-icons wicon-039-pin\"><\/span><span>Pin<\/span><\/div>",
                        "wicon-065-whatsapp": "<div class=\"wicon-select\"><span class=\"wicon-woody-icons wicon-065-whatsapp\"><\/span><span>Whatsapp<\/span><\/div>",
                        "wicon-056-horse": "<div class=\"wicon-select\"><span class=\"wicon-woody-icons wicon-056-horse\"><\/span><span>Horse<\/span><\/div>",
                        "wicon-004-youtube": "<div class=\"wicon-select\"><span class=\"wicon-woody-icons wicon-004-youtube\"><\/span><span>Youtube<\/span><\/div>",
                        "wicon-038-pin-contour": "<div class=\"wicon-select\"><span class=\"wicon-woody-icons wicon-038-pin-contour\"><\/span><span>Pin contour<\/span><\/div>",
                        "wicon-006-linkedin": "<div class=\"wicon-select\"><span class=\"wicon-woody-icons wicon-006-linkedin\"><\/span><span>Linkedin<\/span><\/div>",
                        "wicon-017-telechargement": "<div class=\"wicon-select\"><span class=\"wicon-woody-icons wicon-017-telechargement\"><\/span><span>Telechargement<\/span><\/div>",
                        "wicon-024-loupe": "<div class=\"wicon-select\"><span class=\"wicon-woody-icons wicon-024-loupe\"><\/span><span>Loupe<\/span><\/div>",
                        "wicon-041-lit": "<div class=\"wicon-select\"><span class=\"wicon-woody-icons wicon-041-lit\"><\/span><span>Lit<\/span><\/div>",
                        "wicon-050-muet": "<div class=\"wicon-select\"><span class=\"wicon-woody-icons wicon-050-muet\"><\/span><span>Muet<\/span><\/div>",
                        "wicon-040-imprimante": "<div class=\"wicon-select\"><span class=\"wicon-woody-icons wicon-040-imprimante\"><\/span><span>Imprimante<\/span><\/div>",
                        "wicon-060-favoris": "<div class=\"wicon-select\"><span class=\"wicon-woody-icons wicon-060-favoris\"><\/span><span>Favoris<\/span><\/div>",
                        "wicon-042-lien": "<div class=\"wicon-select\"><span class=\"wicon-woody-icons wicon-042-lien\"><\/span><span>Lien<\/span><\/div>",
                        "wicon-064-github": "<div class=\"wicon-select\"><span class=\"wicon-woody-icons wicon-064-github\"><\/span><span>Github<\/span><\/div>",
                        "wicon-057-walk": "<div class=\"wicon-select\"><span class=\"wicon-woody-icons wicon-057-walk\"><\/span><span>Walk<\/span><\/div>",
                        "wicon-052-mal-entendant": "<div class=\"wicon-select\"><span class=\"wicon-woody-icons wicon-052-mal-entendant\"><\/span><span>Mal entendant<\/span><\/div>",
                        "wicon-013-smiley-excellent": "<div class=\"wicon-select\"><span class=\"wicon-woody-icons wicon-013-smiley-excellent\"><\/span><span>Smiley excellent<\/span><\/div>",
                        "wicon-030-etoile-contour": "<div class=\"wicon-select\"><span class=\"wicon-woody-icons wicon-030-etoile-contour\"><\/span><span>Etoile contour<\/span><\/div>",
                        "wicon-035-fleche-precedent": "<div class=\"wicon-select\"><span class=\"wicon-woody-icons wicon-035-fleche-precedent\"><\/span><span>Fleche precedent<\/span><\/div>",
                        "wicon-032-coeur-contour": "<div class=\"wicon-select\"><span class=\"wicon-woody-icons wicon-032-coeur-contour\"><\/span><span>Coeur contour<\/span><\/div>",
                        "wicon-001-station-tire-fesse": "<div class=\"wicon-select\"><span class=\"wicon-woody-icons wicon-001-station-tire-fesse\"><\/span><span>Station tire fesse<\/span><\/div>",
                        "wicon-002-station-biathlon": "<div class=\"wicon-select\"><span class=\"wicon-woody-icons wicon-002-station-biathlon\"><\/span><span>Station biathlon<\/span><\/div>",
                        "wicon-011-station-snowboard": "<div class=\"wicon-select\"><span class=\"wicon-woody-icons wicon-011-station-snowboard\"><\/span><span>Station snowboard<\/span><\/div>",
                        "wicon-006-station-montagne": "<div class=\"wicon-select\"><span class=\"wicon-woody-icons wicon-006-station-montagne\"><\/span><span>Station montagne<\/span><\/div>",
                        "wicon-014-station-webcam": "<div class=\"wicon-select\"><span class=\"wicon-woody-icons wicon-014-station-webcam\"><\/span><span>Station webcam<\/span><\/div>",
                        "wicon-000-station-teleski": "<div class=\"wicon-select\"><span class=\"wicon-woody-icons wicon-000-station-teleski\"><\/span><span>Station teleski<\/span><\/div>",
                        "wicon-009-station-ski-alpin": "<div class=\"wicon-select\"><span class=\"wicon-woody-icons wicon-009-station-ski-alpin\"><\/span><span>Station ski alpin<\/span><\/div>",
                        "wicon-003-station-flocon": "<div class=\"wicon-select\"><span class=\"wicon-woody-icons wicon-003-station-flocon\"><\/span><span>Station flocon<\/span><\/div>",
                        "wicon-005-station-luge": "<div class=\"wicon-select\"><span class=\"wicon-woody-icons wicon-005-station-luge\"><\/span><span>Station luge<\/span><\/div>",
                        "wicon-010-station-ski-de-fond": "<div class=\"wicon-select\"><span class=\"wicon-woody-icons wicon-010-station-ski-de-fond\"><\/span><span>Station ski de fond<\/span><\/div>",
                        "wicon-013-station-soleil": "<div class=\"wicon-select\"><span class=\"wicon-woody-icons wicon-013-station-soleil\"><\/span><span>Station soleil<\/span><\/div>",
                        "wicon-007-station-raquettes": "<div class=\"wicon-select\"><span class=\"wicon-woody-icons wicon-007-station-raquettes\"><\/span><span>Station raquettes<\/span><\/div>",
                        "wicon-008-station-ski": "<div class=\"wicon-select\"><span class=\"wicon-woody-icons wicon-008-station-ski\"><\/span><span>Station ski<\/span><\/div>",
                        "wicon-004-station-forfait": "<div class=\"wicon-select\"><span class=\"wicon-woody-icons wicon-004-station-forfait\"><\/span><span>Station forfait<\/span><\/div>",
                        "wicon-012-station-snowshoes": "<div class=\"wicon-select\"><span class=\"wicon-woody-icons wicon-012-station-snowshoes\"><\/span><span>Station snowshoes<\/span><\/div>"
                    },
                    "default_value": false,
                    "allow_null": 0,
                    "multiple": 0,
                    "ui": 1,
                    "ajax": 1,
                    "return_format": "value",
                    "placeholder": ""
                },
                {
                    "key": "field_5e393cd74d27b",
                    "label": "Lien",
                    "name": "link",
                    "type": "link",
                    "instructions": "",
                    "required": 0,
                    "conditional_logic": 0,
                    "wrapper": {
                        "width": "80",
                        "class": "",
                        "id": ""
                    },
                    "return_format": "array"
                }
            ]
        }
    ],
    "location": [
        [
            {
                "param": "post_type",
                "operator": "==",
                "value": "post"
            }
        ]
    ],
    "menu_order": 0,
    "position": "normal",
    "style": "default",
    "label_placement": "top",
    "instruction_placement": "label",
    "hide_on_screen": "",
    "active": 1,
    "description": "Groupe de champs à cloner",
    "modified": 1599128641
}