{
    "key": "group_5b042ba749e73",
    "title": "Map marker",
    "fields": [
        {
            "key": "field_5b042bee0f9e0",
            "label": "Marqueur",
            "name": "",
            "type": "tab",
            "instructions": "",
            "required": 0,
            "conditional_logic": 0,
            "wrapper": {
                "width": "",
                "class": "",
                "id": ""
            },
            "placement": "top",
            "endpoint": 0
        },
        {
            "key": "field_5b042cb50f9e5",
            "label": "Position",
            "name": "map_position",
            "type": "google_map",
            "instructions": "",
            "required": 0,
            "conditional_logic": 0,
            "wrapper": {
                "width": "",
                "class": "",
                "id": ""
            },
            "center_lat": "",
            "center_lng": "",
            "zoom": 12,
            "height": ""
        },
        {
            "key": "field_5b042c380f9e3",
            "label": "Icône",
            "name": "marker_woody_icon",
            "type": "select",
            "instructions": "",
            "required": 0,
            "conditional_logic": 0,
            "wrapper": {
                "width": "",
                "class": "",
                "id": ""
            },
            "choices": {},
            "default_value": [],
            "allow_null": 1,
            "multiple": 0,
            "ui": 1,
            "ajax": 1,
            "return_format": "value",
            "placeholder": ""
        },
        {
            "key": "field_5bc5b3fd37205",
            "label": "Couleur du marqueur",
            "name": "marker_color",
            "type": "button_group",
            "instructions": "",
            "required": 0,
            "conditional_logic": 0,
            "wrapper": {
                "width": "",
                "class": "",
                "id": ""
            },
            "choices": {
                "primary": "Couleur principale",
                "secondary": "Couleur secondaire",
                "black": "Noir",
                "darkgray": "Gris foncé",
                "lightgray": "Gris clair"
            },
            "allow_null": 0,
            "default_value": "primary",
            "layout": "horizontal",
            "return_format": "value"
        },
        {
            "key": "field_5b042bd40f9df",
            "label": "Vignette",
            "name": "",
            "type": "tab",
            "instructions": "",
            "required": 0,
            "conditional_logic": 0,
            "wrapper": {
                "width": "",
                "class": "",
                "id": ""
            },
            "placement": "top",
            "endpoint": 0
        },
        {
            "key": "field_5b042c040f9e1",
            "label": "Titre",
            "name": "title",
            "type": "text",
            "instructions": "",
            "required": 0,
            "conditional_logic": 0,
            "wrapper": {
                "width": "",
                "class": "",
                "id": ""
            },
            "default_value": "",
            "placeholder": "",
            "prepend": "",
            "append": "",
            "maxlength": ""
        },
        {
            "key": "field_5b042c180f9e2",
            "label": "Description",
            "name": "description",
            "type": "textarea",
            "instructions": "",
            "required": 0,
            "conditional_logic": 0,
            "wrapper": {
                "width": "",
                "class": "",
                "id": ""
            },
            "default_value": "",
            "placeholder": "",
            "maxlength": "",
            "rows": 3,
            "new_lines": "br"
        },
        {
            "key": "field_5b042bb10f9de",
            "label": "Image",
            "name": "img",
            "type": "image",
            "instructions": "",
            "required": 0,
            "conditional_logic": 0,
            "wrapper": {
                "width": "50",
                "class": "",
                "id": ""
            },
            "return_format": "array",
            "preview_size": "thumbnail",
            "library": "all",
            "min_width": 640,
            "min_height": "",
            "min_size": "",
            "max_width": "",
            "max_height": "",
            "max_size": "",
            "mime_types": "jpeg, jpg, png, gif"
        },
        {
            "key": "field_5b05205f97c50",
            "label": "Lien",
            "name": "link",
            "type": "link",
            "instructions": "",
            "required": 0,
            "conditional_logic": 0,
            "wrapper": {
                "width": "50",
                "class": "",
                "id": ""
            },
            "return_format": "array"
        }
    ],
    "location": [
        [
            {
                "param": "post_type",
                "operator": "==",
                "value": "post"
            }
        ]
    ],
    "menu_order": 0,
    "position": "normal",
    "style": "default",
    "label_placement": "top",
    "instruction_placement": "label",
    "hide_on_screen": "",
    "active": 1,
    "description": "Créer un marqueur  (Cloné dans le groupe \"Carte géo manuelle\")",
    "modified": 1539685746
}
